EasyMenu3/EasyMenu3.py
EasyMenu3/__init__.py
EasyMenu3/formatter.py
easymenu3-0.3.1.dist-info/METADATA
easymenu3-0.3.1.dist-info/WHEEL
easymenu3-0.3.1.dist-info/top_level.txt
easymenu3-0.3.1.dist-info/RECORD
