Metadata-Version: 2.2
Name: easymenu3
Version: 0.3.1
Summary: A simple and customizable menu system for CLI applications.
Home-page: https://github.com/pitterpatter22/EasyMenu3
Author: PitterPatter
Author-email: pitter@pitterpatter.io
Classifier: Programming Language :: Python :: 3
Classifier: License :: OSI Approved :: MIT License
Classifier: Operating System :: OS Independent
Requires-Python: >=3.6
Requires-Dist: pyfiglet
Requires-Dist: icecream
Dynamic: author
Dynamic: author-email
Dynamic: classifier
Dynamic: description
Dynamic: description-content-type
Dynamic: home-page
Dynamic: requires-dist
Dynamic: requires-python
Dynamic: summary
